weight_training_tracker/__init__.py
weight_training_tracker/console_helper.py
weight_training_tracker/constants.py
weight_training_tracker/file_utils.py
weight_training_tracker/main.py
weight_training_tracker/parser.py
weight_training_tracker/summarize_workout_session.py
weight_training_tracker/system_caller.py
weight_training_tracker/workout_exercise.py
weight_training_tracker/workout_session.py
weight_training_tracker/workout_set.py
weight_training_tracker/conf/config.yaml
weight_training_tracker-0.16.1.dist-info/AUTHORS.rst
weight_training_tracker-0.16.1.dist-info/METADATA
weight_training_tracker-0.16.1.dist-info/WHEEL
weight_training_tracker-0.16.1.dist-info/entry_points.txt
weight_training_tracker-0.16.1.dist-info/top_level.txt
weight_training_tracker-0.16.1.dist-info/RECORD
