Metadata-Version: 2.1
Name: weight_training_tracker
Version: 0.16.1
Summary: A simple CLI-based app for tracking weight training.
Home-page: https://github.com/jai-python3/weight-training-tracker
Author: Jaideep Sundaram
Author-email: jai.python3@gmail.com
Keywords: weight-training-tracker
Classifier: Development Status :: 2 - Pre-Alpha
Classifier: Intended Audience :: Developers
Classifier: Natural Language :: English
Classifier: Programming Language :: Python :: 3
Classifier: Programming Language :: Python :: 3.6
Classifier: Programming Language :: Python :: 3.7
Classifier: Programming Language :: Python :: 3.8
Requires-Python: >=3.6
License-File: AUTHORS.rst
Requires-Dist: Click >=7.0
Requires-Dist: pyfiglet
Requires-Dist: PyYAML
Requires-Dist: Pydantic
Requires-Dist: Rich
Requires-Dist: termcolor
